autoreqgen/__init__.py
autoreqgen/cli.py
autoreqgen/docgen.py
autoreqgen/formatter.py
autoreqgen/requirements.py
autoreqgen/scanner.py
autoreqgen/utils.py
autoreqgen-0.1.28.dist-info/licenses/LICENSE
autoreqgen-0.1.28.dist-info/METADATA
autoreqgen-0.1.28.dist-info/WHEEL
autoreqgen-0.1.28.dist-info/entry_points.txt
autoreqgen-0.1.28.dist-info/top_level.txt
autoreqgen-0.1.28.dist-info/RECORD
