Metadata-Version: 2.4
Name: autoreqgen
Version: 0.1.28
Summary: Smarter pipreqs alternative with code formatting and documentation generation
Home-page: https://github.com/harichselvamc/AutoReqGen
Author: Harichselvam
Author-email: Harichselvam <harichselvamc@gmail.com>
License: MIT
Project-URL: Homepage, https://github.com/harichselvamc/AutoReqGen
Project-URL: Documentation, https://github.com/harichselvamc/AutoReqGen#readme
Project-URL: Repository, https://github.com/harichselvamc/AutoReqGen
Project-URL: Source, https://github.com/harichselvamc/AutoReqGen
Project-URL: Issues, https://github.com/harichselvamc/AutoReqGen/issues
Project-URL: Changelog, https://github.com/harichselvamc/AutoReqGen/releases
Keywords: pipreqs,automation,requirements,docgen,formatter
Classifier: Development Status :: 4 - Beta
Classifier: Intended Audience :: Developers
Classifier: License :: OSI Approved :: MIT License
Classifier: Programming Language :: Python
Classifier: Programming Language :: Python :: 3
Classifier: Programming Language :: Python :: 3.8
Classifier: Programming Language :: Python :: 3.9
Classifier: Programming Language :: Python :: 3.10
Classifier: Programming Language :: Python :: 3.11
Classifier: Programming Language :: Python :: 3.12
Classifier: Topic :: Software Development
Classifier: Topic :: Software Development :: Build Tools
Classifier: Environment :: Console
Classifier: Operating System :: OS Independent
Requires-Python: >=3.8
License-File: LICENSE
Requires-Dist: typer>=0.9.0
Requires-Dist: click>=8.1.0
Provides-Extra: format
Requires-Dist: black>=23.0.0; extra == "format"
Requires-Dist: isort>=5.10.0; extra == "format"
Requires-Dist: autopep8>=2.0.0; extra == "format"
Provides-Extra: watch
Requires-Dist: watchdog>=2.1.0; extra == "watch"
Provides-Extra: dotenv
Requires-Dist: python-dotenv>=1.0.0; extra == "dotenv"
Provides-Extra: dev
Requires-Dist: pytest; extra == "dev"
Requires-Dist: coverage; extra == "dev"
Requires-Dist: mypy; extra == "dev"
Requires-Dist: ruff; extra == "dev"
Requires-Dist: types-setuptools; extra == "dev"
Dynamic: author
Dynamic: home-page
Dynamic: license-file
Dynamic: requires-python
